Metadata-Version: 1.1
Name: brainboard
Version: 0.0.0
Summary: 
